en_mi_club_api/__init__.py
en_mi_club_api/config.py
en_mi_club_api/database.py
en_mi_club_api/enums.py
en_mi_club_api/exceptions.py
en_mi_club_api/main.py
en_mi_club_api/utils.py
en_mi_club_api/auth/__init__.py
en_mi_club_api/auth/constants.py
en_mi_club_api/auth/crud.py
en_mi_club_api/auth/endpoints.py
en_mi_club_api/auth/enums.py
en_mi_club_api/auth/exceptions.py
en_mi_club_api/auth/middlewares.py
en_mi_club_api/auth/schemas.py
en_mi_club_api/auth/utils.py
en_mi_club_api/benefits/__init__.py
en_mi_club_api/benefits/exceptions.py
en_mi_club_api/benefits/schemas.py
en_mi_club_api/benefits/utils.py
en_mi_club_api/benefits/in_person_benefits/__init__.py
en_mi_club_api/benefits/in_person_benefits/crud.py
en_mi_club_api/benefits/in_person_benefits/endpoints.py
en_mi_club_api/benefits/in_person_benefits/models.py
en_mi_club_api/benefits/in_person_benefits/schemas.py
en_mi_club_api/benefits/online_benefits/__init__.py
en_mi_club_api/benefits/online_benefits/crud.py
en_mi_club_api/benefits/online_benefits/endpoints.py
en_mi_club_api/benefits/online_benefits/models.py
en_mi_club_api/benefits/online_benefits/schemas.py
en_mi_club_api/commerces/__init__.py
en_mi_club_api/commerces/crud.py
en_mi_club_api/commerces/endpoints.py
en_mi_club_api/commerces/exceptions.py
en_mi_club_api/commerces/models.py
en_mi_club_api/commerces/schemas.py
en_mi_club_api/commerces/contact_form/__init__.py
en_mi_club_api/commerces/contact_form/crud.py
en_mi_club_api/commerces/contact_form/endpoints.py
en_mi_club_api/commerces/contact_form/exceptions.py
en_mi_club_api/commerces/contact_form/models.py
en_mi_club_api/commerces/contact_form/schemas.py
en_mi_club_api/plans/__init__.py
en_mi_club_api/plans/crud.py
en_mi_club_api/plans/endpoints.py
en_mi_club_api/plans/exceptions.py
en_mi_club_api/plans/models.py
en_mi_club_api/plans/schemas.py
en_mi_club_api/raffles/__init__.py
en_mi_club_api/raffles/constants.py
en_mi_club_api/raffles/crud.py
en_mi_club_api/raffles/endpoints.py
en_mi_club_api-0.6.0.dist-info/METADATA
en_mi_club_api-0.6.0.dist-info/WHEEL
en_mi_club_api-0.6.0.dist-info/top_level.txt
en_mi_club_api-0.6.0.dist-info/RECORD
