Metadata-Version: 2.1
Name: en-mi-club-api
Version: 0.6.0
Summary: API entities for En Mi Club
Author: Ingeniasoft
Requires-Dist: boto3
Requires-Dist: email-validator
Requires-Dist: fastapi
Requires-Dist: fastapi-cli
Requires-Dist: passlib
Requires-Dist: psycopg2
Requires-Dist: PyJWT
Requires-Dist: pydantic ==2.7.4
Requires-Dist: pydantic-core ==2.18.4
Requires-Dist: pydantic-settings ==2.3.3
Requires-Dist: python-dateutil
Requires-Dist: python-dotenv
Requires-Dist: python-multipart
Requires-Dist: rut-chile
Requires-Dist: sqlalchemy
Requires-Dist: uvicorn
